{"cameraMode":{"drawMode":0,"name":"Shaded","section":"Shading Mode"},"sceneLighting":false,"audioPlay":false,"sceneViewState":{"showFog":true,"showMaterialUpdate":false,"showSkybox":false,"showFlares":true,"showImageEffects":true,"showParticleSystems":true},"in2DMode":false,"pivot":{"x":-2.167133331298828,"y":-8.940338134765625,"z":5.55677604675293},"rotation":{"x":-0.3669991195201874,"y":0.3432886600494385,"z":-0.14790378510951997,"w":-0.8518151640892029},"size":136.27157592773438,"orthographic":false}